<?xml version="1.0" encoding="UTF-8"?>
<STEP-ProductInformation ContextID="Context1" WorkspaceID="Main" UseContextLocale="false">
    <Qualifiers>
        <Qualifier ID="en-US">
            <DimensionPointLink DimensionPointID="en-US"></DimensionPointLink>
        </Qualifier>
    </Qualifiers>
    <ListsOfValues>
        <ListOfValue ID="LicenseType" ParentID="List Of Values group root" AllowUserValueAddition="false" UseValueID="true">
            <Name QualifierID="en-US">License Type</Name>
            <Validation BaseType="text" MinValue="" MaxValue="" MaxLength="100" InputMask=""></Validation>
            <ValueGroup ID="FD">
                <Value>Fixed Duration</Value>
            </ValueGroup>
            <ValueGroup ID="PERM">
                <Value>Permanent</Value>
            </ValueGroup>
            <ValueGroup ID="TEMP">
                <Value>Temporary</Value>
            </ValueGroup>
            <ValueGroup ID="TRL">
                <Value>Trial</Value>
            </ValueGroup>
        </ListOfValue>
    </ListsOfValues>
</STEP-ProductInformation>